[
    {
      "image": "https://i.ibb.co.com/qsDnJ1x/image.png",
      "title": "The Anatomy of a Civil Claim: Case Study and Legal Implications",
      "description": "An exploration of a civil claim, analyzing its components and legal implications in depth."
    },
    {
      "image": "https://i.ibb.co.com/yXmmDCv/image.png",
      "title": "Property Disputes Unveiled: A Real Estate Law Case Study",
      "description": "Insights into a key real estate law case and its legal impact."
    },
    {
      "image": "https://i.ibb.co.com/c1FFrQS/img.png",
      "title": "The Complexities of Custody: A Family Law Case Analysis",
      "description": "An analysis of a family law case, focusing on legal issues in custody, divorce, and support."
    },
    {
      "image": "https://i.ibb.co.com/HqYzSFV/img.png",
      "title": "The Anatomy of a Civil Claim: Case Study and Legal Implications",
      "description": "An exploration of a civil claim, analyzing its components and legal implications in depth."
    },
    {
      "image": "https://i.ibb.co.com/FBkb192/img-1.png",
      "title": "Property Disputes Unveiled: A Real Estate Law Case Study",
      "description": "Insights into a key real estate law case and its legal impact."
    },
    {
      "image": "https://i.ibb.co.com/nbq7x68/img-2.png",
      "title": "The Complexities of Custody: A Family Law Case Analysis",
      "description": "An analysis of a family law case, focusing on legal issues in custody, divorce, and support."
    },
    {
      "image": "https://i.ibb.co.com/nbq7x68/img-2.png",
      "title": "The Complexities of Custody: A Family Law Case Analysis",
      "description": "An analysis of a family law case, focusing on legal issues in custody, divorce, and support."
    },
    {
      "image": "https://i.ibb.co.com/FBkb192/img-1.png",
      "title": "Property Disputes Unveiled: A Real Estate Law Case Study",
      "description": "Insights into a key real estate law case and its legal impact."
    },
    {
      "image": "https://i.ibb.co.com/HqYzSFV/img.png",
      "title": "Real Estate Law: Buying and Selling Property",
      "description": "Explore the legal aspects of real estate transactions, from contracts to closing."
    },
    {
      "image": "https://i.ibb.co.com/c1FFrQS/img.png",
      "title": "Environmental Law: Protecting Our Planet",
      "description": "A look at the regulations designed to safeguard the environment and promote sustainability."
    },
    {
      "image": "https://i.ibb.co.com/yXmmDCv/image.png",
      "title": "Tax Law Simplified: What You Need to Know",
      "description": "An overview of tax laws and how they impact individuals and businesses."
    },
    {
      "image": "https://i.ibb.co.com/qsDnJ1x/image.png",
      "title": "Consumer Protection: Knowing Your Rights",
      "description": "Learn how consumer protection laws ensure fair treatment and prevent fraud."
    },
    


    {
        "image": "https://i.ibb.co.com/yXmmDCv/image.png",
        "title": "Tax Law Simplified: What You Need to Know",
        "description": "An overview of tax laws and how they impact individuals and businesses."
      },
      {
        "image": "https://i.ibb.co.com/qsDnJ1x/image.png",
        "title": "Consumer Protection: Knowing Your Rights",
        "description": "Learn how consumer protection laws ensure fair treatment and prevent fraud."
      },
    {
      "image": "https://i.ibb.co.com/HqYzSFV/img.png",
      "title": "Real Estate Law: Buying and Selling Property",
      "description": "Explore the legal aspects of real estate transactions, from contracts to closing."
    },
    {
      "image": "https://i.ibb.co.com/c1FFrQS/img.png",
      "title": "Environmental Law: Protecting Our Planet",
      "description": "A look at the regulations designed to safeguard the environment and promote sustainability."
    },
    {
        "image": "https://i.ibb.co.com/nbq7x68/img-2.png",
        "title": "The Complexities of Custody: A Family Law Case Analysis",
        "description": "An analysis of a family law case, focusing on legal issues in custody, divorce, and support."
      },
      {
        "image": "https://i.ibb.co.com/FBkb192/img-1.png",
        "title": "Property Disputes Unveiled: A Real Estate Law Case Study",
        "description": "Insights into a key real estate law case and its legal impact."
      }
  ]
  